Workbook
Name Aporte: Investment!$D$15
Name Dividendos: Investment!$D$19
Name Patrimônio: Investment!$D$18
Name Qtd_Anos: Investment!$D$16
Name Rendimento_Carteira: Investment!$D$11
Name Salario: Investment!$D$10
Name Sugestão_Investimento: Investment!$D$12
Name Taxa_Mensal: Investment!$D$17

Sheet Investment
B9: CONFIGURAÇÕES
B10: Salário | D10: 2356
B11: Rendimento Carteira | D11: 0.009
B12: Sugestão de Investimento | D12: =D10*30% -> 706.8
B14: INVESTIMENTO MENSAL
B15: Quanto investir por mês? | D15: 250
B16: Por Quantos Anos? | D16: 2
B17: Taxa de Rendimento Mensal? | D17: 0.01079
B18: Patrimônio Acumulado? | D18: =FV(Taxa_Mensal,Qtd_Anos*12,Aporte*-1) -> 6806.9068
B19: Dividendos Mensais? | D19: =Patrimônio*Rendimento_Carteira -> 61.262161
B21: Cenários | D21: Dividendo
A22: 2 | B22: Quanto em 2 Anos? | C22: =FV($D$17,$A22*12,$D$15*-1) -> 6806.9068 | D22: =C22*Rendimento_Carteira -> 61.262161
A23: 5 | B23: Quanto em 5 Anos? | C23: =FV($D$17,$A23*12,$D$15*-1) -> 20944.228 | D23: =C23*Rendimento_Carteira -> 188.49806
A24: 10 | B24: Quanto em 10 Anos? | C24: =FV($D$17,$A24*12,$D$15*-1) -> 60821.053 | D24: =C24*Rendimento_Carteira -> 547.38948
A25: 20 | B25: Quanto em 20 Anos? | C25: =FV($D$17,$A25*12,$D$15*-1) -> 281299.6 | D25: =C25*Rendimento_Carteira -> 2531.6964
A26: 30 | B26: Quanto em 30 Anos? | C26: =FV($D$17,$A26*12,$D$15*-1) -> 1080542.4 | D26: =C26*Rendimento_Carteira -> 9724.8817
B28: PERFIL | C28: Conservador
B29: VALOR A SER INVESTIDO POR MÊS | C29: =Aporte -> 250
B31: TIPO DE FII | C31: Percentual Sugerido | D31: Valores
B32: PAPEL | C32: =VLOOKUP($C$28&"-"&B32,Planilha1!$A:$D,4,FALSE) -> 0.3 | D32: =C32*$C$29 -> 75
B33: TIJOLO | C33: =VLOOKUP($C$28&"-"&B33,Planilha1!$A:$D,4,FALSE) -> 0.5 | D33: =C33*$C$29 -> 125
B34: HÍBRIDOS | C34: =VLOOKUP($C$28&"-"&B34,Planilha1!$A:$D,4,FALSE) -> 0.1 | D34: =C34*$C$29 -> 25
B35: FOFs | C35: =VLOOKUP($C$28&"-"&B35,Planilha1!$A:$D,4,FALSE) -> 0.1 | D35: =C35*$C$29 -> 25
B36: DESENVOLVIMENTO | C36: =VLOOKUP($C$28&"-"&B36,Planilha1!$A:$D,4,FALSE) -> 0 | D36: =C36*$C$29 -> 0
B37: HOTELARIAS | C37: =VLOOKUP($C$28&"-"&B37,Planilha1!$A:$D,4,FALSE) -> 0 | D37: =C37*$C$29 -> 0
D38: =SUM(D32:D37) -> 250

Sheet Planilha1
A2: CHAVE | B2: PERFIL | C2: TIPOS DE FII | D2: %
A3: =B3&"-"&C3 -> Conservador-PAPEL | B3: Conservador | C3: PAPEL | D3: 0.3 | H3: %
A4: =B4&"-"&C4 -> Conservador-TIJOLO | B4: Conservador | C4: TIJOLO | D4: 0.5 | G4: Moderado-TIJOLO | H4: =VLOOKUP(G4,$A:$D,4,FALSE) -> 0.35
A5: =B5&"-"&C5 -> Conservador-HÍBRIDOS | B5: Conservador | C5: HÍBRIDOS | D5: 0.1
A6: =B6&"-"&C6 -> Conservador-FOFs | B6: Conservador | C6: FOFs | D6: 0.1
A7: =B7&"-"&C7 -> Conservador-DESENVOLVIMENTO | B7: Conservador | C7: DESENVOLVIMENTO | D7: 0
A8: =B8&"-"&C8 -> Conservador-HOTELARIAS | B8: Conservador | C8: HOTELARIAS | D8: 0
A9: =B9&"-"&C9 -> Moderado-PAPEL | B9: Moderado | C9: PAPEL | D9: 0.32
A10: =B10&"-"&C10 -> Moderado-TIJOLO | B10: Moderado | C10: TIJOLO | D10: 0.35
A11: =B11&"-"&C11 -> Moderado-HÍBRIDOS | B11: Moderado | C11: HÍBRIDOS | D11: 0.08
A12: =B12&"-"&C12 -> Moderado-FOFs | B12: Moderado | C12: FOFs | D12: 0.05
A13: =B13&"-"&C13 -> Moderado-DESENVOLVIMENTO | B13: Moderado | C13: DESENVOLVIMENTO | D13: 0.1
A14: =B14&"-"&C14 -> Moderado-HOTELARIAS | B14: Moderado | C14: HOTELARIAS | D14: 0.1
A15: =B15&"-"&C15 -> Agressivo-PAPEL | B15: Agressivo | C15: PAPEL | D15: 0.5
A16: =B16&"-"&C16 -> Agressivo-TIJOLO | B16: Agressivo | C16: TIJOLO | D16: 0.1
... A20: =B20&"-"&C20 -> Agressivo-HOTELARIAS | B20: Agressivo | C20: HOTELARIAS | D20: 0.1
